zc_test_mcp_demo/__init__.py
zc_test_mcp_demo-0.1.0.dist-info/METADATA
zc_test_mcp_demo-0.1.0.dist-info/WHEEL
zc_test_mcp_demo-0.1.0.dist-info/entry_points.txt
zc_test_mcp_demo-0.1.0.dist-info/RECORD
