Metadata-Version: 2.4
Name: zc-test-mcp-demo
Version: 0.1.0
Summary: Add your description here
Author-email: cj9l <52595917@qq.com>
Requires-Python: >=3.13
Requires-Dist: mcp[cli]>=1.11.0
